xml7shi/__init__.py
xml7shi/xml7shi.py
xml7shi-0.1.0.dist-info/LICENSE
xml7shi-0.1.0.dist-info/METADATA
xml7shi-0.1.0.dist-info/WHEEL
xml7shi-0.1.0.dist-info/top_level.txt
xml7shi-0.1.0.dist-info/RECORD
