Metadata-Version: 2.1
Name: xml7shi
Version: 0.1.0
Summary: Simple XML parser without tag structure validation
Home-page: https://github.com/7shi/xml7shi
Author: 7shi
Author-email: 7shi@live.jp
License-File: LICENSE
